{
  "description": "项目配置文件",
  "packOptions": {
    "ignore": []
  },
  "setting": {
    "bundle": false,
    "userConfirmedBundleSwitch": false,
    "urlCheck": false,
    "scopeDataCheck": false,
    "coverView": true,
    "es6": true,
    "postcss": true,
    "compileHotReLoad": false,
    "preloadBackgroundData": false,
    "minified": true,
    "autoAudits": false,
    "newFeature": false,
    "uglifyFileName": false,
    "uploadWithSourceMap": true,
    "useIsolateContext": true,
    "nodeModules": true,
    "enhance": false,
    "useCompilerModule": true,
    "userConfirmedUseCompilerModuleSwitch": false,
    "useMultiFrameRuntime": false,
    "useApiHook": true,
    "showShadowRootInWxmlPanel": true,
    "packNpmManually": false,
    "enableEngineNative": false,
    "packNpmRelationList": [],
    "minifyWXSS": true
  },
  "compileType": "miniprogram",
  "libVersion": "2.14.0",
  "appid": "wxa79ffc51783229f9",
  "projectname": "一起跑",
  "debugOptions": {
    "hidedInDevtools": []
  },
  "scripts": {},
  "isGameTourist": false,
  "simulatorType": "wechat",
  "simulatorPluginLibVersion": {},
  "condition": {
    "search": {
      "list": []
    },
    "conversation": {
      "list": []
    },
    "game": {
      "list": []
    },
    "plugin": {
      "list": []
    },
    "gamePlugin": {
      "list": []
    },
    "miniprogram": {
      "list": []
    }
  }
}